picsl_brainmold/__init__.py
picsl_brainmold/__main__.py
picsl_brainmold/brainmold.py
picsl_brainmold/slab_postproc.py
picsl_brainmold-0.0.3.dist-info/METADATA
picsl_brainmold-0.0.3.dist-info/WHEEL
picsl_brainmold-0.0.3.dist-info/licenses/LICENSE
picsl_brainmold-0.0.3.dist-info/RECORD
