Metadata-Version: 2.4
Name: picsl_brainmold
Version: 0.0.3
Summary: BrainMold: Package for 3D printing cutting molds for ex vivo MRI
Project-URL: Homepage, https://github.com/pyushkevich/brainmold
Author-email: Paul Yushkevich <pyushkevich@gmail.com>
License-File: LICENSE
Classifier: Development Status :: 4 - Beta
Classifier: Intended Audience :: Science/Research
Classifier: License :: OSI Approved :: MIT License
Classifier: Operating System :: OS Independent
Classifier: Programming Language :: Python :: 3
Classifier: Topic :: Scientific/Engineering :: Medical Science Apps.
Requires-Python: >=3.8
Requires-Dist: matplotlib
Requires-Dist: numpy
Requires-Dist: picsl-c3d>=1.4.2.2
Requires-Dist: simpleitk
